omni/__init__.py
omni/client.py
omni/config.py
omni/embed.py
omni/utils.py
omni_analytics_sdk-2.1.0.dist-info/METADATA
omni_analytics_sdk-2.1.0.dist-info/WHEEL
omni_analytics_sdk-2.1.0.dist-info/licenses/LICENSE
omni_analytics_sdk-2.1.0.dist-info/RECORD
