Metadata-Version: 2.4
Name: omni-analytics-sdk
Version: 2.1.0
Summary: Omni Analytics Python SDK.
Project-URL: Homepage, https://camoag.github.io/omni-sdk/stable/
Project-URL: Repository, https://github.com/camoag/omni-sdk
Project-URL: Documentation, https://camoag.github.io/omni-sdk/stable/
Author-email: Daniel Tiesling <daniel.tiesling@camo.ag>
License-File: LICENSE
Classifier: License :: OSI Approved :: MIT License
Classifier: Operating System :: OS Independent
Classifier: Programming Language :: Python :: 3
Requires-Python: <3.11,>=3.10
Requires-Dist: requests
